python_undef/__init__.py
python_undef/__main__.py
python_undef-1.1.0.dist-info/METADATA
python_undef-1.1.0.dist-info/WHEEL
python_undef-1.1.0.dist-info/licenses/LICENSE
python_undef-1.1.0.dist-info/RECORD
