Metadata-Version: 2.4
Name: python_undef
Version: 1.1.0
Summary: Python keep header and undefined header in pyconfig.h
Project-URL: homepage, https://github.com/Locked-chess-official/python_undef
Author-email: Locked-chess-official <13140752715@163.com>
License: MIT
License-File: LICENSE
